bytedlark_ai_idp/__init__.py
bytedlark_ai_idp-0.0.1.dist-info/METADATA
bytedlark_ai_idp-0.0.1.dist-info/WHEEL
bytedlark_ai_idp-0.0.1.dist-info/top_level.txt
bytedlark_ai_idp-0.0.1.dist-info/RECORD
